{
  "timestamp": "2025-07-31T06:10:50.013Z",
  "tests": [
    {
      "name": "Dark Mode Activation",
      "passed": true,
      "details": {
        "hasDarkClass": true,
        "themeStorage": "dark"
      }
    }
  ],
  "summary": {
    "passed": 1,
    "failed": 0,
    "warnings": 0
  },
  "error": {
    "message": "page.evaluate: SyntaxError: Failed to execute 'querySelector' on 'Document': '[class*=\"card\"]:has-text(\"Vendor Aging Balance\"), .card:has(*:contains(\"Vendor Aging Balance\"))' is not a valid selector.\n    at eval (eval at evaluate (:291:30), <anonymous>:2:34)\n    at UtilityScript.evaluate (<anonymous>:293:16)\n    at UtilityScript.<anonymous> (<anonymous>:1:44)",
    "stack": "page.evaluate: SyntaxError: Failed to execute 'querySelector' on 'Document': '[class*=\"card\"]:has-text(\"Vendor Aging Balance\"), .card:has(*:contains(\"Vendor Aging Balance\"))' is not a valid selector.\n    at eval (eval at evaluate (:291:30), <anonymous>:2:34)\n    at UtilityScript.evaluate (<anonymous>:293:16)\n    at UtilityScript.<anonymous> (<anonymous>:1:44)\n    at /Users/tmr/Desktop/MadaDashboardV10/test-vendors-darkmode-monitor.js:65:40"
  }
}